README.md
setup.cfg
setup.py
dlai/__init__.py
dlai/colab_utils.py
dlai/imports.py
dlai/mlai.py
dlai/tfai.py
dlai/utils.py
dlai.egg-info/PKG-INFO
dlai.egg-info/SOURCES.txt
dlai.egg-info/dependency_links.txt
dlai.egg-info/requires.txt
dlai.egg-info/top_level.txt