Metadata-Version: 2.1
Name: dlai
Version: 0.0.17
Summary: DL & ML helper library
Home-page: UNKNOWN
Author: Laura Lu
Author-email: new4spam@gmail.com
License: UNKNOWN
Platform: UNKNOWN
Classifier: Programming Language :: Python :: 3
Classifier: License :: OSI Approved :: MIT License
Classifier: Operating System :: OS Independent
